tests/test_Server.py
tests/test_PuzzlePlayer.py
tests/conftest.py
tests/__init__.py
GamesmanPuzzles-0.0.4.dist-info/METADATA
GamesmanPuzzles-0.0.4.dist-info/WHEEL
GamesmanPuzzles-0.0.4.dist-info/top_level.txt
GamesmanPuzzles-0.0.4.dist-info/LICENSE
GamesmanPuzzles-0.0.4.dist-info/RECORD
puzzlesolver/_puzzlesolverc.cpython-36m-x86_64-linux-gnu.so
puzzlesolver/util.py
puzzlesolver/__init__.py
puzzlesolver/solvers/solver.py
puzzlesolver/solvers/indexsolver.py
puzzlesolver/solvers/sqlitesolver.py
puzzlesolver/solvers/generalsolver.py
puzzlesolver/solvers/__init__.py
puzzlesolver/puzzles/graphpuzzle.py
puzzlesolver/puzzles/chairs.py
puzzlesolver/puzzles/npuzzle.py
puzzlesolver/puzzles/topspin.py
puzzlesolver/puzzles/bishop.py
puzzlesolver/puzzles/lightsout.py
puzzlesolver/puzzles/pegSolitaire.py
puzzlesolver/puzzles/__init__.py
puzzlesolver/puzzles/hanoi/hanoi.py
puzzlesolver/puzzles/hanoi/__init__.py
puzzlesolver/puzzles/_models/puzzle.py
puzzlesolver/puzzles/_models/serverPuzzle.py
puzzlesolver/puzzles/_models/__init__.py
puzzlesolver/python/_puzzlesolverc.cpython-36m-x86_64-linux-gnu.so
puzzlesolver/python/util.py
puzzlesolver/python/__init__.py
puzzlesolver/python/solvers/solver.py
puzzlesolver/python/solvers/indexsolver.py
puzzlesolver/python/solvers/sqlitesolver.py
puzzlesolver/python/solvers/generalsolver.py
puzzlesolver/python/solvers/__init__.py
puzzlesolver/python/puzzles/graphpuzzle.py
puzzlesolver/python/puzzles/chairs.py
puzzlesolver/python/puzzles/npuzzle.py
puzzlesolver/python/puzzles/topspin.py
puzzlesolver/python/puzzles/bishop.py
puzzlesolver/python/puzzles/hanoi.py
puzzlesolver/python/puzzles/lightsout.py
puzzlesolver/python/puzzles/pegSolitaire.py
puzzlesolver/python/puzzles/__init__.py
puzzlesolver/python/puzzles/_models/puzzle.py
puzzlesolver/python/puzzles/_models/serverPuzzle.py
puzzlesolver/python/puzzles/_models/__init__.py
